agilepoint/__init__.py
agilepoint/_utils.py
agilepoint/admin.py
agilepoint/exceptions.py
agilepoint/workflow.py
agilepoint-0.0.6.dist-info/DESCRIPTION.rst
agilepoint-0.0.6.dist-info/METADATA
agilepoint-0.0.6.dist-info/RECORD
agilepoint-0.0.6.dist-info/WHEEL
agilepoint-0.0.6.dist-info/metadata.json
agilepoint-0.0.6.dist-info/top_level.txt
