Metadata-Version: 2.0
Name: agilepoint
Version: 0.0.6
Summary: AgilePoint API lib
Home-page: https://github.com/blade2005/py-agilepoint
Author: Craig Davis
Author-email: cdavis@alertlogic.com
License: GPLv3
Keywords: agilepoint bpm bpms
Platform: UNKNOWN
Classifier: Development Status :: 3 - Alpha
Classifier: Intended Audience :: Developers
Classifier: Topic :: Software Development :: Build Tools
Classifier: License :: OSI Approved :: GNU General Public License v3 (GPLv3)
Classifier: Programming Language :: Python :: 2
Classifier: Programming Language :: Python :: 2.7
Requires-Dist: hammock
